jsonport/__init__.py
jsonport/core.py
jsonport-1.0.2.dist-info/licenses/LICENSE
tests/__init__.py
tests/test_jsonport.py
jsonport-1.0.2.dist-info/METADATA
jsonport-1.0.2.dist-info/WHEEL
jsonport-1.0.2.dist-info/top_level.txt
jsonport-1.0.2.dist-info/RECORD
