Metadata-Version: 2.4
Name: jsonport
Version: 1.0.2
Summary: A high-performance Python library for serialization and deserialization of Python objects to and from JSON. Supports dataclasses, enums, datetime, collections, and more.
Home-page: https://github.com/luan1schons/jsonport
Author: Luan Schons
Author-email: Luan1Schons <luanschons2000@gmail.com>, LuigiTaka <luigimendeszanchett@gmail.com>
License: MIT
Project-URL: Homepage, https://github.com/Luan1Schons/JsonPort
Project-URL: Repository, https://github.com/Luan1Schons/JsonPort
Project-URL: Issues, https://github.com/Luan1Schons/JsonPort/issues
Classifier: Development Status :: 5 - Production/Stable
Classifier: Intended Audience :: Developers
Classifier: Programming Language :: Python :: 3
Classifier: Programming Language :: Python :: 3.7
Classifier: Programming Language :: Python :: 3.8
Classifier: Programming Language :: Python :: 3.9
Classifier: Programming Language :: Python :: 3.10
Classifier: Programming Language :: Python :: 3.11
Classifier: Programming Language :: Python :: 3.12
Classifier: Programming Language :: Python :: 3.13
Classifier: Topic :: Software Development :: Libraries :: Python Modules
Requires-Python: >=3.7
License-File: LICENSE
Provides-Extra: test
Requires-Dist: pytest>=7.0.0; extra == "test"
Requires-Dist: pytest-cov>=4.0.0; extra == "test"
Requires-Dist: pytest-benchmark>=4.0.0; extra == "test"
Provides-Extra: dev
Requires-Dist: black>=22.0.0; extra == "dev"
Requires-Dist: flake8>=4.0.0; extra == "dev"
Requires-Dist: mypy>=0.950; extra == "dev"
Requires-Dist: pre-commit>=2.15.0; extra == "dev"
Dynamic: author
Dynamic: home-page
Dynamic: license-file
Dynamic: requires-python
